pyweatherbitdata/__init__.py
pyweatherbitdata/api.py
pyweatherbitdata/const.py
pyweatherbitdata/data.py
pyweatherbitdata/exceptions.py
pyweatherbitdata/helpers.py
pyweatherbitdata-1.0.15.dist-info/LICENSE.txt
pyweatherbitdata-1.0.15.dist-info/METADATA
pyweatherbitdata-1.0.15.dist-info/WHEEL
pyweatherbitdata-1.0.15.dist-info/top_level.txt
pyweatherbitdata-1.0.15.dist-info/RECORD
