Metadata-Version: 2.1
Name: pyweatherbitdata
Version: 1.0.15
Summary: Python Wrapper for WeatherBit Rest API
Home-page: https://github.com/briis/py-weatherbit
Author: Bjarne Riis
Author-email: bjarne@briis.com
License: MIT
Keywords: Home Assistant,Python,WeatherBit
Classifier: Development Status :: 5 - Production/Stable
Classifier: Intended Audience :: Developers
Classifier: Topic :: Software Development :: Build Tools
Classifier: License :: OSI Approved :: MIT License
Classifier: Programming Language :: Python :: 3.8
Classifier: Programming Language :: Python :: 3.9
Classifier: Programming Language :: Python :: 3.10
License-File: LICENSE.txt
Requires-Dist: aiohttp
